memorylru-1.1.2.dist-info/top_level.txt
memorylru-1.1.2.dist-info/WHEEL
memorylru-1.1.2.dist-info/METADATA
memorylru-1.1.2.dist-info/zip-safe
memorylru-1.1.2.dist-info/RECORD
memorylru/lru.pyi
memorylru/lru.pypy39-pp73-x86-linux-gnu.so
memorylru/__init__.py
memorylru/lru.c
