Metadata-Version: 2.1
Name: memorylru
Version: 1.1.2
Home-page: https://github.com/vangheem/memorylru
License: BSD
Classifier: Development Status :: 4 - Beta
Classifier: Programming Language :: Python :: 3.7
Classifier: Topic :: Software Development :: Libraries :: Python Modules
